{"inkVersion":20,"root":[["^Welcome to the bonfire, Unkindled One. ",{"#":"Clip.hellofirekeeper"},{"#":"Camera.WitchCam"},"\n",["ev",{"^->":"0.4.$r1"},{"temp=":"$r"},"str",{"->":".^.s"},[{"#n":"$r1"}],"/str","/ev",{"*":"0.c-0","flg":18},{"s":["^The Lords have left their thrones, and must be deliver'd to them.",{"->":"$r","var":true},null]}],["ev",{"^->":"0.5.$r1"},{"temp=":"$r"},"str",{"->":".^.s"},[{"#n":"$r1"}],"/str","/ev",{"*":"0.c-1","flg":18},{"s":["^To this end, I am at thy side.",{"->":"$r","var":true},null]}],{"c-0":["ev",{"^->":"0.c-0.$r2"},"/ev",{"temp=":"$r"},{"->":"0.4.s"},[{"#n":"$r2"}],"\n",{"->":"0.g-0"},{"#f":5}],"c-1":["ev",{"^->":"0.c-1.$r2"},"/ev",{"temp=":"$r"},{"->":"0.5.s"},[{"#n":"$r2"}],"\n",{"->":"0.g-0"},{"#f":5}],"g-0":["^Welcome home, ashen one.","\n","end",["done",{"#f":5,"#n":"g-1"}],{"#f":5}]}],"done",{"#f":1}],"listDefs":{}}